mmq/__init__.py
mmq/metodo_minimos_quadrados.py
mmq-0.0.2.dist-info/METADATA
mmq-0.0.2.dist-info/WHEEL
mmq-0.0.2.dist-info/licenses/LICENSE
mmq-0.0.2.dist-info/RECORD
