Metadata-Version: 2.1
Name: mmq
Version: 0.0.2
Summary: It computes the coeficientes of the MMQ for a given set of 2-D points
Project-URL: Homepage, https://github.com/pypa/sampleproject
Project-URL: Bug Tracker, https://github.com/pypa/sampleproject/issues
Author-email: Igor Jasenovski <igormjsk@gmail.com>
License-File: LICENSE
Classifier: License :: OSI Approved :: MIT License
Classifier: Operating System :: OS Independent
Classifier: Programming Language :: Python :: 3
Requires-Python: >=3.9
